setup.py
Flask_Router.egg-info/PKG-INFO
Flask_Router.egg-info/SOURCES.txt
Flask_Router.egg-info/dependency_links.txt
Flask_Router.egg-info/not-zip-safe
Flask_Router.egg-info/requires.txt
Flask_Router.egg-info/top_level.txt
flask_router/__init__.py
flask_router/tests.py