Metadata-Version: 1.1
Name: Flask-Router
Version: 0.1.0
Summary: Tuned flask's URL routing library
Home-page: http://blog.hardtack.me/
Author: GunWoo Choi
Author-email: 6566gun@gmail.com
License: UNKNOWN
Platform: any
Classifier: Development Status :: 2 - Pre-Alpha
Classifier: Intended Audience :: Developers
